Workbook

Sheet SUMÁRIO
B3: Nome completo:
B4: Navegador(a):
B5: Nome do Produto:
B6: Início da Preparação: | D6: 45663
B7: Data do Lançamento: | D7: 45712
D8: Esta é a data da Abertura de Carrinho.
B11: Progresso do seu Lançamento
B12: =(COUNTIF('PRÉ-REQUISITOS'!B25:B68,TRUE)+COUNTIF('CLI e AI'!B47:B68,TRUE)+COUNTIF(Lançamento!B25:B68,TRUE)+COUNTIF('Pós-Lançamento'!B20:B68,TRUE))/165 -> 0
C13: =IFERROR(__xludf.DUMMYFUNCTION("SPARKLINE(B12,{""charttype"",""bar"";""color1"",""#38a036"";""max"",1})"),"")
A16: VISÃO GERAL
C18: Pré-requisitos - tudo o que você já preparou até aqui
B19: ✅ | C19: Definir Nicho, Avatar e Roma
B20: ✅ | C20: Definir Oferta e Método
B21: ✅ | C21: Ter criado Redes Sociais que comunique o produto
B22: ✅ | C22: Frequência de Conteúdo para crescimento e nutrição de audiência
B23: ✅ | C23: Ter planejado os criativos
B24: ✅ | C24: Ter criado as páginas de captação e obrigado
B25: ✅ | C25: Ter criado a campanha de captação
B28: =CONCATENATE("ETAPA DE PREPARAÇÃO de ", TEXT(SUMÁRIO!$D$6,"DD/MM"), " a ", TEXT(SUMÁRIO!$D$6+(((SUMÁRIO!$D$7-21)-SUMÁRIO!$D$6)*1)-1,"DD/MM")) -> ETAPA DE PREPARAÇÃO de 06/01 a 02/02
B29: Durante esta etapa, você irá preparar tudo o que precisa para começar a sua captação.
B30: Revisar as etapas de Pré-requisitos
B31: Planejamento de Conteúdo de Aquecimento
B32: Criar as notificações de pré-lançamento
B35: =CONCATENATE("ETAPA DE CONSTRUÇÃO DE LISTA DE INSCRITOS (CLI) e AQUECIMENTO DE INSCRITOS (AI) - DE ", TEXT($D$7-21,"DD/MM"), " ATÉ ", TEXT($D$7-7,"DD/MM")) -> ETAPA DE CONSTRUÇÃO DE LISTA DE INSCRITOS (CLI) e AQUECIMENTO DE INSCRITOS (AI) - DE 03/02 ATÉ 17/02
B36: A sua captação de leads iniciou! Agora, é necessário aquecer a sua lista de inscritos, antecipando o lançamento!
B37: Captação de Leads
B38: Publicação dos Conteúdos de Aquecimento
B39: Otimização da campanha de captação
B40: Notificações de Lançamento
B41: Escrever o Script dos CPLs
B42: Criar as notificações de Lançamento
B45: =CONCATENATE("ETAPA DE PRÉ-LANÇAMENTO ", TEXT($D$7-7,"DD/MM"), " ATÉ ", TEXT($D$7-1,"DD/MM"), " (7 dias)") -> ETAPA DE PRÉ-LANÇAMENTO 17/02 ATÉ 23/02 (7 dias)
B46: Abertura dos CPL's
B47: Remarketing de CPL
B48: Criação da Campanha de Remarketing de Carrinho
B49: Planejamento dos Conteúdos de Carrinho Aberto
B50: Notificações de Carrinho
B51: Planejamento da Recuperação de Vendas
B54: =CONCATENATE("ETAPA DE LANÇAMENTO - DE ", TEXT($D$7,"DD/MM"), " ATÉ ", TEXT($D$7+4,"DD/MM")) -> ETAPA DE LANÇAMENTO - DE 24/02 ATÉ 28/02
B55: Nesta etapa você vai transmitir o Webinário, abrir o carrinho e iniciar a recuperação de vendas.
B56: Abertura do Carrinho
B57: Recuperação de Vendas
B58: Publicação dos Conteúdos de Carrinho Aberto
B59: Disparos de Notificações de Fechamento de Carrinho
B62: =CONCATENATE("ETAPA DE PÓS-LANÇAMENTO - DE ", TEXT($D$7+5,"DD/MM"), " ATÉ ", TEXT($D$7+7,"DD/MM")) -> ETAPA DE PÓS-LANÇAMENTO - DE 01/03 ATÉ 03/03
B63: O seu lançamento acabou e agora é a hora de preparar o Debriefing para solicitar a Análise de Lançamento
B64: Fechamento do Carrinho
B65: Preenchimento do Debriefing
B66: Solicitação da Análise de Lançamento

Sheet PRÉ-REQUISITOS
A1: PRÉ-REQUISITOS (este ciclo foi executado durante o estudo dos Fundamentos da Jornada)
A2: Lançamento Clássico
B3: =(COUNTIF(B18:B127,TRUE)/50) -> 0
C4: =IFERROR(__xludf.DUMMYFUNCTION("SPARKLINE(B3,{""charttype"",""bar"";""color1"",""#38a036"";""max"",1})"),"")
B7: 📄 | C7: DOCUMENTOS NECESSÁRIOS NESTE CICLO
C8: Caso tenha dúvidas de como utilizar esses documentos, acesse os tutoriais | D8: -> | E8: https://hotmart.com/pt-BR/club/am-insider/products/6130002/content/PeAg8qMPOW
B10: Launch Drive para produção do lançamento | D10: -> | E10: 1 | F10: Pasta 1) Documentação de Lançamento -> 2) Nicho, Avatar e Roma
E11: 2 | F11: Pasta 1) Documentação de Lançamento -> 4) Oferta - Visão Geral
E12: 3 | F12: Pasta 3) Criativos -> Mapa de Criativos
E13: 4 | F13: Pasta 2) Páginas
E14: 5 | F14: Pasta 4) Notificações -> 1) AI - Aquecimento de Inscritos -> 1) E-mails
E15: 6 | F15: Pasta 1) Documentação de Lançamento -> 8) Planilha de Tráfego
B18: PRÉ-REQUISITOS
B19: Para ter um bom lançamento, é necessário ter uma base sólida e bem definida. Você acabou de passar por uma fase que te desenvolveu para chegar até aqui com tudo isso pronto. Agora é o momento de revisar o que foi feito e se certificar que nada passou batido
B21: BASES
B22: O Nicho, Avatar, Roma e Método são as bases que vão delinear toda a sua estratégia de lançamento. Garanta que não exista nenhuma lacuna na definição dessas bases.
B23: 💻 Caso seja necessário, assista aos materiais enviados sobre o tema | D23: -> | F23: https://hotmart.com/pt-BR/club/am-insider/products/6130002/content/oODgEj2x7P
B25: FALSE | C25: Revise seu Nicho, Avatar e Roma
C26: Use o documento 1 listado em Documentos Necessários disponível no início dessa seção.
B27: FALSE | C27: Revise sua Oferta e Método
C28: Use o documento 2 listado em Documentos Necessários disponível no início dessa seção.
B30: AUDIÊNCIA
B31: Para que você consiga construir uma audiência qualificada, que se interessa pelo seu produto, é preciso comunicar a oportunidade de maneira certa nas suas redes sociais. Certifique-se que os seus perfis nas redes sociais estejam organizados de maneira que comunique a oportunidade de Roma.
B32: 💻 Caso sinta necessidade, assista aos materiais enviados sobre o tema | E32: -> | F32: https://hotmart.com/pt-BR/club/am-insider/products/6130002/content/3eaQBP8keg
B34: INSTAGRAM
B35: FALSE | C35: 1. Confirme que a sua conta do Instagram esteja configurada como um Perfil Comercial
B36: FALSE | C36: 2. Certifique-se de que a Roma está na bio
B37: FALSE | C37: 3. Coloque 1 post fixado quebrando objeções do seu avatar
B38: FALSE | C38: 4. Crie 1 destaque contando a história do expert. Exemplo: Comece por aqui - Jornada do Heroi (aqui você vai colocar a história do expert relacionando à história do método)
B39: FALSE | C39: 5. Crie 1 destaque explicando como os conteúdos do expert podem ajudar. Exemplo: Como eu posso te ajudar (mostre o valor do seu conteúdo) - Deve explicar a Roma - Deve explicar para quem se destina os conteúdos (avatar)
B40: FALSE | C40: 6. Crie 1 destaque com provas e depoimento dos alunos. Exemplo: Resultado dos alunos, caso tenha (depoimentos em vídeo, mensagens enviadas por direct, whatsapp etc...)
B42: FACEBOOK
B43: FALSE | C43: 1. Coloque uma capa que comunique a sua Roma exatamente como ela é
B45: YOUTUBE
B46: FALSE | C46: 1. Coloque uma capa que comunique a sua Roma
B47: FALSE | C47: 2. Grave um vídeo de boas-vindas e fixe na página inicial do seu canal
B49: CONTEÚDO
B50: Durante a Fase 02 você aprendeu a planejar conteúdos que comuniquem com o público certo. Além de publicar conteúdos, para intensificar o crescimento da audiência, você pode fazer a distribuição paga dos seus conteúdos.
B51: 🎯 | C51: Material complementar: ID de Construção de Audiência | D51: -> | F51: https://hotmart.com/pt-BR/club/am-insider/products/6130002/content/z7rBNrA27j
B53: FALSE | C53: Se planeje para postar pelo menos 5 reels/nutella e 1 raíz por semana
B55: CRIATIVOS
B56: Você já aprendeu o que são Criativos e como criá-los, na Fase 03. Para iniciar a fase de captação, você precisa dos criativos prontos, então agora é a hora de botar a mão na massa!
B57: 💻 Caso sinta necessidade, assista aos materiais enviados sobre o tema | D57: -> | F57: https://hotmart.com/pt-BR/club/am-insider/products/6130002/content/ROxVq6mKeD
B58: Acesse à biblioteca de criativos, caso precise de inspiração | D58: -> | F58: https://hotmart.com/pt-BR/club/am-insider/products/6130002/content/b4K9JA0N7X?track=zK4k0vMoeY
C59: Use o documento 3 listado em Documentos Necessários disponível no início dessa seção.
B61: FALSE | C61: Liste ideia de, pelo menos, 10 estilos de criativos
B62: FALSE | C62: Adapte os Criativos para conectar com o seu Avatar
B63: FALSE | C63: Defina e Escreva no seu Mapa de Criativos 2.0 o estilo de cada um dos 10 criativos
B64: FALSE | C64: Grave e edite os 10 criativos estruturado anteriormente
B65: FALSE | C65: [OPCIONAL] Faça um criativo que comunique sobre as lives de aquecimento, para ser distribuído para as leads já inscritas no lançamento.
B67: FERRAMENTAS
B68: Na Fase 03, você aprendeu a criar e configurar corretamente todas as páginas necessárias para o seu Lançamento Semente. Neste passo você deve revisar e se certificar de que as páginas estejam configuradas corretamente.
B69: 💻 | C69: Conteúdo de apoio, caso seja necessário revisar algum ponto: | D69: -> | F69: https://hotmart.com/pt-BR/club/am-insider/products/6130002/content/R4jbq2wA4a
B71: PÁGINAS
B72: Para ter uma página completa, você precisa: - inserir o link do grupo de WhatsApp na Página de Obrigado. - inserir o link da Pesquisa de Avatar na automação do e-mail de Obrigado.
C73: Use o documento 4, listado em Documentos Necessários, disponível no início desta seção.
C75: Certifique-se de que:
B76: FALSE | C76: Tenha criado uma comunidade com um nome, capa e descrição que identifique o seu evento.
B77: FALSE | C77: Adicionou administradores para as comunidades. Dica: por segurança tenha, pelo menos, 3 administradores.
B78: FALSE | C78: Tenha incluído o link da comunidade na página de Obrigado e na automação do e-mail de obrigado.
B79: FALSE | C79: Tenha inserido o link da pesquisa de avatar na automação do e-mail de obrigado.
C81: Na configuração das páginas, confira se:
B82: FALSE | C82: O Pixel do Facebook foi criado corretamente
B83: FALSE | C83: O pixel do Facebook foi incluído em todas as suas páginas
B84: FALSE | C84: O Tag Manager foi implementado
B85: FALSE | C85: O domínio foi apontado para o HotmartPages
C86: Revise o conteúdo e a configuração todas as páginas
B87: FALSE | C87: Inscrição
B88: FALSE | C88: Obrigado
B89: FALSE | C89: Termos de Uso
B90: FALSE | C90: Política de Privacidade
B91: FALSE | C91: Blog de Lançamento
B92: FALSE | C92: Página de Vendas
B94: E-MAIL MARKETING
B95: Garanta que tenha criado todas as automações de e-mails necessárias para comunicar suas leads sobre o lançamento.
C96: Use o documento 5, listado em Documento Necessários, disponível no início desta seção
B98: FALSE | C98: 1. Crie o seu formulário de inscrição na sua ferramenta de email marketing - 📓 Tutorial Hotmart - O que É e Como Criar um Formulário
B99: FALSE | C99: 2. Integre o seu formulário com as suas páginas de lançamento - 📓 Tutorial Hotmart - Como Integrar o Send com o Pages
B100: FALSE | C100: 3. Teste o seu processo de inscrição e garanta que a inscrição está sendo registrada na sua ferramenta de email marketing com a tag correta
B101: FALSE | C101: 4. Crie uma sequência na sua ferramenta de email marketing - 📓 Tutorial Hotmart - O que É e Como Criar uma Sequência
B102: FALSE | C102: 5. Programe o Email 1) EMAIL DE OBRIGADO + PESQUISA como o primeiro passo da sequência de e-mails, para ser disparado logo após a lead confirmar a inscrição
B103: FALSE | C103: 6. Programe o Email 2) CONVITE GRUPO DE WHATSAPP como um passo dentro sequência do passo anterior, para ser disparado 1 dia depois da lead se inscrever
B104: FALSE | C104: 7. Integre o Listboss da Hotmart - 📓 Tutorial Hotmart - O que é e como integrar o Listboss?
B106: CAMPANHA DE TRÁFEGO
B107: Você já estudou sobre como configurar uma campanha de tráfego com o objetivo de captação, para criar a sua lista de leads para o lançamento. Agora chegou o momento de organizar a sua estratégia e conferir se tudo está configurado corretamente.
C108: Utilize o documento 6, listado em Documentos Necessários, disponível no início desta seção.
B110: FALSE | C110: Defina o Planejamento de Investimento e registre em seu arquivo do Launch Drive
B111: FALSE | C111: Com base na sua Meta de Leads Total, utilize a Planilha de Tráfego para planejar a sua Meta de Leads Diária e Meta de Orçamento Diário
B112: 💻 | C112: Conteúdo de apoio sobre Planejamento de Investimento | D112: -> | F112: https://hotmart.com/pt-BR/club/am-insider/products/6130002/content/k7Q1rdpx7y
B114: FACEBOOK | D114: GOOGLE
B115: FALSE | C115: Criar Pixel do Facebook - 👨‍🏫 Aula de Criação de Pixel no Facebook | E115: FALSE | F115: Criar Global Site Tag e Snippet de Evento de Conversão - 👨‍🏫 Aula de Criação a Global Site Tag e o Snippet de Evento de Conversão
B116: FALSE | C116: Preencher o doc "PIXELS E SCRIPTS" - 👨‍🏫 Tutorial de como usar o doc Pixels e Scripts | E116: FALSE | F116: Preencher o doc "PIXELS E SCRIPTS" - 👨‍🏫 Tutorial de como usar o doc Pixels e Scripts
B117: FALSE | C117: Implemente o Tag Manager - 👨‍🏫 Aula de Implementação do Google Tag Manager | E117: FALSE | F117: Implemente o Tag Manager - 👨‍🏫 Aula de Implementação do Google Tag Manager
B118: FALSE | C118: Configure a sua campanha de captação de leads na Meta - 👨‍🏫 Aula Configurações Iniciais para Captação de Leads | E118: FALSE | F118: Configure a sua captação de leads - 👨‍🏫 Aula Configurações Iniciais para Captaçao de Leads no Google
B119: FALSE | C119: Verifique o domínio do Facebook 👨‍🏫 Aula de verificação do Domínio da sua Página no Facebook | E119: FALSE | F119: Criação de Públicos - 👨‍🏫 Aula de Criação de Públicos no Google
B120: FALSE | C120: Criação de Públicos - 👨‍🏫 Aula de Criação de Públicos no Facebook | E120: FALSE | F120: Criar todos os públicos de de usuários do Youtube
B121: FALSE | C121: Crie um público de Envolvimento de 30, 60, 90, 180 e 365 | E121: FALSE | F121: Crie uma campanha de vídeo com o objetivo de Conversão
B122: FALSE | C122: Crie sua Campanha de Captação - 👨‍🏫 Criação da Campanha de Captação de Leads | E122: FALSE | F122: Use os grupos de anúncios os seus públicos de segmentos personalizados e envolvimento. - Envolvimento Youtube: adicionou um video a uma playlist, curtiu um vídeo e compartilhou um vídeo - Segmentos Personalizados: Nos segmentos personalizados crie públicos de interesse utilizando suas principais palavras-chaves
B123: FALSE | C123: Crie os conjuntos de anúncios de remarketing da página de inscrição, Envolvimento, Lookalikes e Interesses | E123: FALSE | F123: Use de 3 a 4 anúncios iniciais para a captação adicionando o link do vídeo não-listado no Youtube
B124: FALSE | C124: Use de 3 a 4 anúncios iniciais para a captação adicionando os criativos de vídeo/imagem, texto principal (copy), título e CTA | E124: FALSE | F124: =CONCATENATE("Programe a campanha para começar dia ",TEXT(SUMÁRIO!$D$7-21,"DD/MM")) -> Programe a campanha para começar dia 03/02
...

Sheet Preparação
A1: =CONCATENATE("Preparação de ", TEXT(SUMÁRIO!$D$6,"DD/MM"), " até ", TEXT(SUMÁRIO!$D$6+(((SUMÁRIO!$D$7-3)-SUMÁRIO!$D$6)*0.63)-1,"DD/MM")) -> Preparação de 06/01 até 02/02
A2: Lançamento Clássico
B3: =(COUNTIF(B65:B129,TRUE)/29) -> 0
C4: =IFERROR(__xludf.DUMMYFUNCTION("SPARKLINE(B3,{""charttype"",""bar"";""color1"",""#38a036"";""max"",1})"),"")
C8: O QUE ESPERAR NESTE CICLO
B9: Você já configurou todas as ferramentas necessárias para executar o seu lançamento, agora chegou a hora de implementar! Nessa fase, você deverá planejar seus conteúdos de aquecimento e escrever as copies das notificações de pré-lançamento que serão enviadas durante o período de Captação.
B10: Caso tenha dificuldade para concluir alguma atividade da fase de "Pré-requisitos", você pode ir ajustando as atividades paralelamente às atividades desta fase.
B11: ⚠️ Importante! Enquanto estiver neste ciclo, você deverá produzir e postar conteúdo, seguindo a frequência de pelo menos 4 reels e 1 raíz por semana.
B14: 💻 | C14: MATERIAIS DE APOIO DESTE CICLO (somente se precisar)
B15: CONTEÚDO
B16: 1 | C16: ID de Conteúdo Raíz | D16: -> | F16: https://hotmart.com/pt-BR/club/am-insider/products/6130002/content/NOwQyD3Mem
B17: 2 | C17: ID de Reels | D17: -> | F17: https://hotmart.com/pt-BR/club/am-insider/products/6130002/content/M7G9bwd94w
B18: DISTRIBUIÇÃO (opcional)
B19: 3 | C19: Curso de Tráfego 2.0 Módulo de Distribuição | D19: -> | F19: https://hotmart.com/pt-BR/club/am-insider/products/6130002/content/2OMJAXK146
B22: 📄 | C22: DOCUMENTOS NECESSÁRIOS NESTE CICLO
B23: Content Drive para produção e armazenamento de dados de distribuição | D23: -> | E23: 1 | F23: Pasta 1) Produção -> 1) Gerador de Raíz; 2) Gerador de Reels
E24: 2 | F24: Pasta 2) Distribuição -> 4) Métricas Reels e Distribuição de Conteúdo
E25: 3 | F25: Pasta 2) Distribuição -> 4) Crescimento de Audiência Google ADS
E26: 4 | F26: Pasta 1) Produção -> 4) Gerador de Conteúdo de Aquecimento
B28: Launch Drive para produção do lançamento | D28: -> | E28: 1 | F28: Pasta 4) Notificações
B31: PRODUÇÃO E PUBLICAÇÃO DE CONTEÚDO
B32: Enquanto você está preparando o seu lançamento, é necessário que mantenha a frequência de conteúdo. Caso tenha dúvida em como estruturar os conteúdos, utilize os materiais complementares e as instruções abaixo.
B34: 📢 Atenção! É ideal que você mantenha uma frequência de semanal, pelo menos:
B35: 5 reels / nutellas | E35: 1 raíz
B37: RAÍZ
B38: 📄 | C38: Utilize o documento 1, listado no início desta seção, para roteirizar o conteúdo raíz
B39: 🎯 | C39: Material complementar - Conteúdo Raíz
B40: FALSE | C40: Escolha as linhas editoriais e os temas de modo que consiga manter consistência e fazer 1 raíz por semana.
B41: FALSE | C41: Escreva as Estruturas de Roteiros dos temas listados, crie uma cópia para cada tema na aba "Estrutura de Roteiro" do arquivo 1) GERADOR DE RAIZ
B43: NUTELLA / REELS
B44: 📄 | C44: Utilize o documento 1, listado no início desta seção, para roteirizar seus reels
B45: 🎯 | C45: Material complementar - Reels
B46: FALSE | C46: Defina temas que conectam com seu avatar e que estejam alinhados à sua roma para gravar nos reels, seguindo a estrutura orientada no Launch Drive. É ideal que mantenha uma frequência de, pelo menos, 5 reels por semana
C47: 💡Você deve pensar na quantidade de reels a serem postados até começar a sua captação, tentando manter a frequência de pelo 5 reels por semana.
B50: Distribuição de Conteúdo
B51: Para o Lançamento Semente, distribuição de conteúdo não é determinante, mas pode ajudar a potencializar o crescimento da sua audiência, além de popular os públicos para a campanha de captação.
B52: 🎯 | C52: Material complementar - Distribuição de Conteúdo
B54: Turbinar - aumentando seu público para o Lançamento
B55: FALSE | C55: Confira seu orçamento para distribuição de acordo com a tabela.
B57: FACEBOOK | E57: GOOGLE
B58: 📄 | C58: Utilize o documento 2, para planilhar as métricas dos reels | E58: 📄 | F58: Utilize o documento 3, para planilhar os conteúdos distribuídos
B59: FALSE | C59: Localize o reels que deseja impulsionar > botão azul > turbinar publicação. Selecione a meta: mais visita ao perfil. | E59: FALSE | F59: Crie uma campanha de vídeo sem meta
B60: FALSE | C60: Configure seu público frio. (passe o mouse para visualizar o passo a passo) | E60: FALSE | F60: Crie os grupos de anúncios de seguimentos personalizados conforme ensinado na aula.
B61: FALSE | C61: Defina o orçamento diário e a duração da campanha que será veiculada, em seguida toque em ‘Avançar’. | E61: FALSE | F61: Adicione os vídeos raízes que você publicou na semana anterior
B62: FALSE | C62: Revise as configurações realizadas e caso esteja tudo certo toque no botão ‘Turbinar publicação’. | E62: FALSE | F62: Publique a campanha Nas próximas semanas, você só vai ter que duplicar essa campanha, atualizar a data e trocar os vídeos)
B65: Planejamento de Conteúdos de Aquecimento
B66: Durante a etapa de Construção da Lista de Inscritos (CLI), você deverá fazer conteúdos que antecipem o evento de lançamento (CPLs), direcionado para as leads inscritas e para o público que ainda não se inscreveu. Esses conteúdos fazem parte do "Aquecimento dos Inscritos" e você pode utilizar todos os canais de contato com o avatar para publicá-los: lives, reels, stories e áudios nos grupos.
B67: Os Conteúdos de Aquecimento devem gerar Desejo para participar do Evento de Pré-lançamento e sempre apresentar um CTA para inscrição. Exemplo: "Se inscreva no link na bio"
B68: Os temas definidos deverão enfraquecer as principais OBJEÇÕES do avatar em relação à ROMA e devem ser replicados nos Reels, Stories, Lives de Aquecimento e Áudios de Whatsapp.
B69: 📄 | C69: Use o documento 4 listado em Materiais de Apoio descrito no início dessa seção.
C71: Defina 10 Temas para serem trabalhados em seus conteúdos | E71: Escreva abaixo cada um dos temas definidos
B72: FALSE | C72: 1ª Tema:
B73: FALSE | C73: 2ª Tema:
B74: FALSE | C74: 3ª Tema:
B75: FALSE | C75: 4ª Tema:
B76: FALSE | C76: 5ª Tema:
B77: FALSE | C77: 6ª Tema:
B78: FALSE | C78: 7ª Tema:
B79: FALSE | C79: 8ª Tema:
B80: FALSE | C80: 9ª Tema:
B81: FALSE | C81: 10ª Tema:
B83: ÁUDIOS DE WHATSAPP
B84: 💡 | C84: Você deverá enviar um áudio por dia, de domingo à quinta até a data do lançamento.
B85: FALSE | C85: Crie os 10 áudios que serão enviados durante o período de captação.
B87: REELS
B88: 💡 | C88: Você deverá publicar um reels de aquecimento por dia: do dia que inicia a captação de leads até a data do lançamento.
B89: FALSE | C89: Crie a estrutura dos 15 reels a partir dos temas definidos
B91: LIVES DE AQUECIMENTO
B92: 💡 | C92: Serão realizadas 10 lives de aquecimento, sendo de domingo a quinta durante as duas semanas de camptação, até o domingo que antecede o CPL 1.
B93: FALSE | C93: 1. Defina quais as linhas editoriais você vai usar no seu aquecimento. Você pode usar os três intercalando:
C94: 1.1 - Aula de Aquecimento
C95: 1.2 - Perguntas e Respostas
C96: 1.3 - Entrevista
B97: FALSE | C97: Crie a estrutura das 3 lives a partir dos temas definidos
B99: STORIES
B100: 💡 Você deverá replicar os temas definidos anteriormente também nos stories. Aproveite para interagir com a sua audiência abrindo Caixinhas de Perguntas e Caixinha de Contagem Regressiva para o Webinário.
B101: FALSE | C101: Defina os assuntos abordados nos stories de acordo com os temas definidos anteriormente.
C102: Escolha alguma forma de interação com a sua audiência - Caixinha de perguntas - Enquetes - Reações
B105: Notificações de Pré-lançamento
B106: 💡 | C106: As copies de todas as mensagens estão disponíveis em seu Launch Drive.
B108: Notificação de Inscrição
B109: E-mail de "Obrigado + Comunidade do Whatsapp"
B110: No ciclo anterior, você programou os e-mails, agora é preciso adaptar a copy com a sua identidade, para a comunicação com o avatar.
B111: FALSE | C111: Adapte a copy do e-mail de "OBRIGADO + PESQUISA".
B112: FALSE | C112: Adapte a copy do e-mail "CONVITE GRUPO DE WHATSAPP"
B114: Whatsapp - Mensagem de Boas-Vindas
B115: FALSE | C115: Crie uma mensagem de boas-vindas usando o Script BOAS-VINDAS + PESQUISA DE AVATAR disponível no seu Launch Drive (passe o mouse aqui pra ler um exemplo)
B116: FALSE | C116: Armazene essa mensagem na pasta do seu Launch Drive, para ser enviada periodicamente nos grupos do Whatsapp.
B118: Antecipação do Lançamento
B119: E-mail
B120: FALSE | C120: =CONCATENATE("Escreva a notificação de ''Faltam 7 dias'' e se programe para enviar para a sua lista de inscritos no dia ",TEXT(SUMÁRIO!D7-14,"DD/MM")) -> Escreva a notificação de ''Faltam 7 dias'' e se programe para enviar para a sua lista de inscritos no dia 10/02
B121: FALSE | C121: =CONCATENATE("2. Escreva a notificação de ''Faltam 4 dias'' e se programe para enviar para a lista de inscritos no dia ",TEXT(SUMÁRIO!D7-11,"DD/MM")) -> 2. Escreva a notificação de ''Faltam 4 dias'' e se programe para enviar para a lista de inscritos no dia 13/02
B122: FALSE | C122: =CONCATENATE("3. Escreva a notificação de ''É Amanhã'' e se programe para enviar para a lista de inscritos no dia no dia ",TEXT(SUMÁRIO!D7-8,"DD/MM")) -> 3. Escreva a notificação de ''É Amanhã'' e se programe para enviar para a lista de inscritos no dia no dia 16/02
B124: WhatsApp
B125: FALSE | C125: =CONCATENATE("1. Escreva a notificação de ''Faltam 7 dias'' e se programe para enviar no dia ",TEXT(SUMÁRIO!D7-14,"DD/MM")) -> 1. Escreva a notificação de ''Faltam 7 dias'' e se programe para enviar no dia 10/02
B126: FALSE | C126: =CONCATENATE("2. Escreva a notificação de ''Faltam 4 dias'' e se programe para enviar no dia ",TEXT(SUMÁRIO!D7-11,"DD/MM")) -> 2. Escreva a notificação de ''Faltam 4 dias'' e se programe para enviar no dia 13/02
B127: FALSE | C127: =CONCATENATE("3. Escreva a notificação de ''É Amanhã'' e se programe para enviar no dia ",TEXT(SUMÁRIO!D7-8,"DD/MM")) -> 3. Escreva a notificação de ''É Amanhã'' e se programe para enviar no dia 16/02

Sheet CLI e AI
A1: =CONCATENATE("Captação e Aquecimento de Leads - ",TEXT(SUMÁRIO!$D$7-21,"DD/MM")," até ",TEXT(SUMÁRIO!$D$7-8,"DD/MM"),) -> Captação e Aquecimento de Leads - 03/02 até 16/02
A2: Lançamento Clássico
B3: =(COUNTIF(B42:B394,TRUE)/87) -> 0
C4: =IFERROR(__xludf.DUMMYFUNCTION("SPARKLINE(B3,{""charttype"",""bar"";""color1"",""#38a036"";""max"",1})"),"")
C8: O QUE ESPERAR NESTE CICLO
B9: A sua captação de leads começou, o seu maior foco é acompanhar os dados de captação, fazer as otimizações da campanha e aquecer os inscritos.
B10: ⚠️ Você deverá fazer a otimização de orçamento diariamente, otimização de criativos 2x na semana e otimização de públicos 1x na semana.
B11: Além disso, você deverá postar os conteúdos de aquecimento (reels, stories, lives e áudios de WhatsApp) e enviar as notificações de pré-lançamento.
B14: 💻 | C14: MATERIAIS DE APOIO DESTE CICLO (somente se precisar)
B15: CAMPANHA DE CAPTAÇÃO DE LEADS - OTIMIZAÇÃO
B16: 1 | C16: Curso de Tráfego 2.0 - Aulas de Otimização - Facebook / Meta | E16: -> | F16: https://hotmart.com/pt-BR/club/am-insider/products/6130002/content/M7G9pg0V4w
B17: 2 | C17: Curso de Tráfego 2.0 - Aulas de Otimização - Google | F17: https://hotmart.com/pt-BR/club/am-insider/products/6130002/content/y4bVRL3P4R
B19: CAMPANHA DE REMARKETING
B20: 3 | C20: Cursto de Tráfego 2.0 - Criativos de Remarketing | E20: -> | F20: https://hotmart.com/pt-BR/club/am-insider/products/6130002/content/94J9p0MdOg
B21: 4 | C21: Curso de Tráfego 2.0 - Criação da Campanha de Remarketing de Antecipação | F21: https://hotmart.com/pt-BR/club/am-insider/products/6130002/content/gOpb2NqXeJ
B22: 5 | C22: Curso de Tráfego 2.0 - Planejamento de investimento de Remarketing de CPL | F22: https://hotmart.com/pt-BR/club/am-insider/products/6130002/content/k45QmVyN4l
B23: 6 | C23: Curso de Tráfego 2.0 - Criação da Campanha de Remarketing de CPL | F23: https://hotmart.com/pt-BR/club/am-insider/products/6130002/content/37d8aZXX7L
B25: SCRIPT DOS CPLS
B26: 7 | C26: ID de Script para Lançamento Clássico Parte I | E26: -> | F26: https://hotmart.com/pt-BR/club/am-insider/products/6130002/content/y4P9Dgrxex
B27: 8 | C27: ID de Script para Lançamento Clássico Parte II | F27: https://hotmart.com/pt-BR/club/am-insider/products/6130002/content/V7yx9WEqeJ
B30: 📄 | C30: DOCUMENTOS NECESSÁRIOS NESTE CICLO
B31: Launch Drive para produção do lançamento | D31: -> | E31: 1 | F31: Pasta 3) Criativos -> Mapa de Criativos -> Seção REMARKETING - ANTECIPAÇÃO
E32: 2 | F32: Pasta 1) Documentação de Lançamento -> 9) Planilha de Tráfego -> Aba PLANEJAMENTO DE LEADS e Aba PLANEJAMENTO DE CRIATIVOS
E33: 3 | F33: Pasta 6) CPLs e VV -> 1) Script CPL 1
E34: 4 | F34: Pasta 6) CPLs e VV -> 1) Script CPL 2
E35: 5 | F35: Pasta 6) CPLs e VV -> 3) Script CPL 3 e 4) Script VV
E36: 6 | F36: Pasta 1) Documentação de Lançamento -> 9) Planilha de Tráfego -> RMKT
E37: 7 | F37: Pasta 5) Notificações -> 3) Lançamentos -> 1) Email e 2) Whatsapp
B39: Content Drive para produção e e armazenamento de dados de distribuição | D39: -> | E39: 8 | F39: Pasta 1) Produção -> 4) Gerador de Conteúdo de Aquecimento -> Aba Vídeo de Antecipação
B43: =CONCATENATE(TEXT(SUMÁRIO!D7-21,"DD")," de ",TEXT(SUMÁRIO!D7-21,"MMMM")," - Início da Captação de Leads") -> 03 de fevereiro - Início da Captação de Leads
B44: =CONCATENATE("⚠️ Atenção! A sua Captação de Leads começa hoje, ",TEXT(SUMÁRIO!D7-21,"DD/MM")) -> ⚠️ Atenção! A sua Captação de Leads começa hoje, 03/02
B45: ⚠️ ATENÇÃO! Durante o período de Captação você deve Otimizar o Orçamento da sua campanha 1x ao dia todos os dias; Otimizar criativos duas vezes na semana; Otimizar os públicos 1x na semana.
B47: FALSE | C47: Verifique se suas campanhas de captação, programadas na semana passada, estão ativas conforme a data programada
B48: FALSE | C48: Coloque o Link da página captação na bio do Instagram, com um CTA atrativo
B49: FALSE | C49: Crie 1 post antecipando o seu lançamento e fixe no feed no início da captação. Esse post deve explicar sobre o que será o evento, quando e como se inscrever.
B50: FALSE | C50: Coloque 1 post fixado mostrando as provas do seu produto, com depoimentos de alunos, mensagens recebidas, print do direct etc.
B51: FALSE | C51: Envie a mensagem de boas vindas (preparada no ciclo anterior) no grupo do Whatsapp a cada 100 novos leads ou a cada 3 dias.
B54: =CONCATENATE(TEXT(SUMÁRIO!D7-21,"DD")," de ",TEXT(SUMÁRIO!D7-21,"MMMM")," - [OPCIONAL] Campanha de Remarketing de Aquecimento") -> 03 de fevereiro - [OPCIONAL] Campanha de Remarketing de Aquecimento
B55: A campanha de Remarketing de Aquecimento tem por objetivo aumentar o número de visualizações das lives de aquecimento. Isso é muito importante conscientizar a lead sobre oportunidade de Roma, fazendo seeding para o evento de pré-lançamento e a oferta. Programe a campanha para começar 3 dias após o início da captação de leads.
B56: 🎯 | C56: Material complementar - Remarketing de Aquecimento
B58: FALSE | C58: Crie uma campanha de alcance
B59: FALSE | C59: Adicione o conjunto de anúncios de Inscritos no lançamento (público da página de obrigado + página de inscrição 180D + envolvimendo 30D)
B60: FALSE | C60: Crie um anúncio informando sobre as Lives de Aquecimento, com um CTA que encaminhe para a uma Playlist com as Lives de Aquecimento
C61: =CONCATENATE("Programe a campanha para começar dia ",TEXT(SUMÁRIO!D7-11,"DD/MM")) -> Programe a campanha para começar dia 13/02
B64: =CONCATENATE(TEXT(SUMÁRIO!D7-21,"DD")," de ",TEXT(SUMÁRIO!D7-21,"MMMM")," - Conteúdo de AQUECIMENTO") -> 03 de fevereiro - Conteúdo de AQUECIMENTO
B65: FALSE | C65: Publique o Reels com o Tema que foi definido no Ciclo de Preparação.
B66: FALSE | C66: Publique os stories com o tema definido no Ciclo de Preparação.
B67: FALSE | C67: Envie o áudio de whatsapp com o tema definido no Ciclo de Preparação.
B68: FALSE | C68: Realize a 1ª Live de Aquecimento
B71: =CONCATENATE(TEXT(SUMÁRIO!D7-20,"DD")," de ",TEXT(SUMÁRIO!D7-20,"MMMM")," - Criativos de Remarketing") -> 04 de fevereiro - Criativos de Remarketing
C72: No lançamento clássio consideramos uma lista de pelo menos 1000 leads, o que permite que seja relaizadas campanhas de remarketing. Utilizamos campanha de remarketing para três finalidades: - Antecipação do evento de lançamento - CPL no ar - Carrinho aberto. Para cada campanha, são necessárias quantidades de criativos.
B73: 📄 | C73: Utilize o documento 1, para planejar seus criativos de remarketing
B74: 🎯 | C74: Material complementar - Criativos de Remarketing
B76: FALSE | C76: Crie todos os 7 criativos de Lembrete (antecipação e aquecimento)
B77: FALSE | C77: Crie todos os 4 criativos de CPL's no ar
B78: FALSE | C78: Crie todos os 7 criativos de Carrinho Aberto
B81: =CONCATENATE(TEXT(SUMÁRIO!D7-20,"DD")," de ",TEXT(SUMÁRIO!D7-20,"MMMM")," - Otimização da Campanha de Captação") -> 04 de fevereiro - Otimização da Campanha de Captação
B82: Para ter melhores resultados na sua campanha de captação de leads, você deverá fazer a otimização da campanha, a partir do dia seguinte ao início da campanha. Otimização nada mais é do que melhorar os resultados da campanha, a partir dos resultados obtidos até então.
B83: 📄 | C83: Utilize o documento 2, para planilhar as métricas da campanha.
B85: Facebook | E85: Google
B86: 🎯 | C86: Material Complementar - Otimização | E86: 🎯 | F86: Material Complementar - Otimização
B87: FALSE | C87: 1. Otimize o Orçamento da campanha de leads. | E87: FALSE | F87: 1. Otimize o Orçamento da campanha de leads
E88: FALSE | F88: 2. Otimize os ajustes de lance de CPA
B91: =CONCATENATE(TEXT(SUMÁRIO!D7-20,"DD")," de ",TEXT(SUMÁRIO!D7-20,"MMMM")," - Conteúdo de AQUECIMENTO") -> 04 de fevereiro - Conteúdo de AQUECIMENTO
B92: FALSE | C92: Publique o Reels com o Tema que foi definido no Ciclo de Preparação.
B93: FALSE | C93: Publique os stories com o tema definido no Ciclo de Preparação.
B94: FALSE | C94: Envie o áudio de whatsapp com o tema definido no Ciclo de Preparação.
B95: FALSE | C95: Realize a 2ª Live de Aquecimento
B98: =CONCATENATE(TEXT(SUMÁRIO!D7-19,"DD")," de ",TEXT(SUMÁRIO!D7-19,"MMMM")," - Planejamento da Campanha de Remarketing de Antecipação") -> 05 de fevereiro - Planejamento da Campanha de Remarketing de Antecipação
B99: 🎯 | C99: Material complementar - Remarketing de Antecipação
B101: FALSE | C101: Crie um vídeo de 5 minutos antecipando o evento. Aproveite para mostrar a oportunidade do que o avatar aprenderá nos CPLs.
B102: 📄 | C102: Utilize o documento 8 para estruturar o criativo da campanha de Antecipação
B103: FALSE | C103: Crie uma campanha de alcance
B104: FALSE | C104: Adicione o conjunto de anúncios de Inscritos no lançamento (público da página de obrigado 180D + envolvimento 30D)
B105: FALSE | C105: =CONCATENATE("Programe a campanha para começar pelo menos dois antes do CPL1, dia ",TEXT(SUMÁRIO!D7-2,"DD/MM")) -> Programe a campanha para começar pelo menos dois antes do CPL1, dia 22/02
B108: =CONCATENATE(TEXT(SUMÁRIO!D7-19,"DD")," de ",TEXT(SUMÁRIO!D7-19,"MMMM")," - Otimização da Campanha de Captação") -> 05 de fevereiro - Otimização da Campanha de Captação
B109: 📄 | C109: Utilize o documento 2, para planilhar as métricas da campanha.
B111: Facebook | E111: Google
B112: 🎯 | C112: Material Complementar - Otimização | E112: 🎯 | F112: Material Complementar - Otimização
B113: FALSE | C113: Otimize o Orçamento da campanha de leads | E113: FALSE | F113: Otimize o Orçamento da campanha de leads
C114: Otimize os Criativos da campanha na quarta-feira | E114: FALSE | F114: Otimize os ajustes de lance de CPA
C115: Crie um público de quem Vizualizou o Anúncio 25% | E115: FALSE | F115: Otimize os Criativos da campanha na quarta-feira
B118: =CONCATENATE(TEXT(SUMÁRIO!D7-19,"DD")," de ",TEXT(SUMÁRIO!D7-19,"MMMM")," - Conteúdo de AQUECIMENTO") -> 05 de fevereiro - Conteúdo de AQUECIMENTO
B119: FALSE | C119: Publique o Reels com o Tema que foi definido no Ciclo de Preparação.
B120: FALSE | C120: Publique os stories com o tema definido no Ciclo de Preparação.
B121: FALSE | C121: Envie o áudio de whatsapp com o tema definido no Ciclo de Preparação.
B122: FALSE | C122: Realize a 3ª Live de Aquecimento
B125: =CONCATENATE(TEXT(SUMÁRIO!D7-18,"DD")," de ",TEXT(SUMÁRIO!D7-18,"MMMM")," - Roteiro CPL 1") -> 06 de fevereiro - Roteiro CPL 1
B126: 📄 | C126: Utilize o documento 3, para fazer o script do CPL 1
B127: 🎯 | C127: Material Complementar - Script CPL 1
C129: Selecione ao lado o tipo de arquétipo que irá usar Obs: selecione apenas um | E129: FALSE | F129: Jeito Errado / Jeito Certo
E130: FALSE | F130: Oportunidade / Oportunidade Amplificada
B131: FALSE | C131: Escreva o Roteiro do CPL 1 no documento especificado no seu Launch Drive
B134: =CONCATENATE(TEXT(SUMÁRIO!D7-18,"DD")," de ",TEXT(SUMÁRIO!D7-18,"MMMM")," - Otimização da Campanha de Captação") -> 06 de fevereiro - Otimização da Campanha de Captação
B135: 📄 | C135: Utilize o documento 2, para planilhar as métricas da campanha.
B137: Facebook | E137: Google
B138: 🎯 | C138: Material Complementar - Otimização | E138: 🎯 | F138: Material Complementar - Otimização
B139: FALSE | C139: Otimize o Orçamento da campanha de leads | E139: FALSE | F139: Otimize o Orçamento da campanha de leads
C140: Otimize os Públicos da campanha na quinta-feira | E140: FALSE | F140: Otimize os ajustes de lance de CPA
E141: FALSE | F141: Otimize os Públicos da campanha na quinta-feira
...

Sheet Cópia de SEMANA 02 - CLI e AI I
A1: =CONCATENATE("CLI e AI I - ",TEXT(SUMÁRIO!D7-17,"DD/MM")," a ",TEXT(SUMÁRIO!D7-13,"DD/MM")) -> CLI e AI I - 07/02 a 11/02
A3: Semana 2 | Lançamento Semente
B4: =(COUNTIF(B9:B143,TRUE)+COUNTIF(E:E,TRUE))/52 -> 0
C5: =IFERROR(__xludf.DUMMYFUNCTION("SPARKLINE(B4,{""charttype"",""bar"";""color1"",""#38a036"";""max"",1})"),"")
B9: 📅 Agenda da Semana
B10: =CONCATENATE("📌 ",TEXT(SUMÁRIO!D7-21,"DD/MM")," - Call Semana 03") -> 📌 03/02 - Call Semana 03
B13: =CONCATENATE(TEXT(SUMÁRIO!D7-17,"DD")," de ",TEXT(SUMÁRIO!D7-23,"MMMM")," - Whatsapp e Pesquisa de Avatar") -> 07 de fevereiro - Whatsapp e Pesquisa de Avatar
B14: 1. Configurando Comunidade do WhatsApp
B15: 📓 Tutorial de como Criar Comunidade e Convidar Pessoas
B17: FALSE | C17: 1. Escolha um nome para a comunidade que identifique o seu evento e o número para a identificação da comunidade: Exemplo: Jornada 6em7 #1
B18: FALSE | C18: 2. Crie uma “capa” para inserir nas suas comunidades.
B19: FALSE | C19: 3. Certifique-se de adicionar administradores para as comunidades, por segurança no mínimo 3 administradores.
B20: FALSE | C20: 4. A quantidade de comunidades criadas vai depender da sua meta de captação de leads, cada comunidade cabe, em média, 2.000 pessoas.
B21: FALSE | C21: 5. Em cada chip de celular, crie no máximo 50 comunidades.
B22: FALSE | C22: 6. Adicione a descrição nas comunidades.
B24: 3. Mensagem de Boas-Vindas
B25: 📂 Acesse: LAUNCH DRIVE ➔ 5) NOTIFICAÇÕES ➔ 2) WHATSAPP OU TELEGRAM ➔ 1) BOAS VINDAS + PESQUISA
B27: FALSE | C27: 7. Crie uma mensagem de boas-vindas usando o Script BOAS-VINDAS + PESQUISA DE AVATAR disponível no seu Launch Drive (passe o mouse aqui pra ler um exemplo)
B28: FALSE | C28: 8. Depois de criar a mensagem na plataforma, basta selecionar a opção de “boas-vindas” que a mensagem será disparada automaticamente quando a comunidade lotar.
B30: 4. Convidar para a comunidade
B31: Convide sua lista de inscritos no lançamento para entrar no grupo (Distribuição de links)
B33: FALSE | C33: 9. Na página de obrigado do seu lançamento insira o link/botão que leve para a sua comunidade de WhatsApp.
B34: FALSE | C34: 10. No E-mail de confirmação de inscrição disponibilize o link para entrar na comunidade WhatsApp
B35: FALSE | C35: 11. Enviar mensagem de boas vindas à medida que o grupo lotar (caso não lote o grupo, pode mandar mensagem a cada X pessoas que entrarem ou a cada X dias)
B37: Pesquisa de Avatar
B38: 💡 Use o arquivo 6) PESQUISA DE AVATAR disponibilizado no seu Launch Drive e crie a sua pesquisa de avatar que será enviada posteriormente para sua lista
B39: 📂 Acesse: LAUNCH DRIVE ➔ 1) DOCUMENTAÇÃO DE LANÇAMENTO ➔ 6) PESQUISA DE AVATAR
B40: 👨‍🏫 Tutorial de como criar a sua Pesquisa de Avatar
B42: FALSE | C42: 1. Crie uma pesquisa de Avatar que será enviada posteriormente para suas leads no e-mail/mensagem de obrigado.
B44: =CONCATENATE(TEXT(SUMÁRIO!D7-16,"DD")," de ",TEXT(SUMÁRIO!D7-16,"MMMM")," - Configuração das Ferramentas") -> 08 de fevereiro - Configuração das Ferramentas
B45: 💻 Sugestão de conteúdo: ID de Ferramentas para LS
B46: 1. Páginas
B48: FALSE | C48: 1. Aponte o domínio para o HotmartPages - 👨‍🏫 Aula de Como Apontar Domínio
B49: FALSE | C49: 2. Criar página de Inscrição
B50: FALSE | C50: 3. Criar página de Obrigado
B51: FALSE | C51: 4. Criar página de Termos de Uso
B52: FALSE | C52: 5. Criar página de Política de Privacidade
B53: FALSE | C53: 6. Criar página de Replay
B55: 2. Transmissão
B57: FALSE | C57: 1. Configurar transmissão ao vivo no YouTube - 📓 Tutorial de como Configurar Transmissão
B58: FALSE | C58: 2. Habilitar canal para transmissão ao vivo
B59: FALSE | C59: 3. Criar transmissão ao vivo
B60: FALSE | C60: 4. Testar transmissão
B62: 3. E-mail Marketing
B64: FALSE | C64: 1. Crie o seu formulário de inscrição na sua ferramenta de email marketing - 📓 Tutorial Hotmart - O que É e Como Criar um Formulário
B65: FALSE | C65: 2. Integre o seu formulário com as suas páginas de lançamento - 📓 Tutorial Hotmart - Como Integrar o Send com o Pages
B66: FALSE | C66: 3. Teste o seu processo de inscrição e garanta que a inscrição está sendo registrada na sua ferramenta de email marketing com a tag correta
B67: FALSE | C67: 4. Crie uma sequência na sua ferramenta de email marketing - 📓 Tutorial Hotmart - O que É e Como Criar uma Sequência
B68: FALSE | C68: 5. Programe o Email 1) EMAIL DE OBRIGADO + PESQUISA como o primeiro passo da sequência, para ser disparado logo após a lead confirmar a inscrição
C69: 📝 Clique aqui para abrir o modelo do Email de Obrigado
C70: 📝 Clique aqui para abrir o modelo de Pesquisa do Avatar
B71: FALSE | C71: 6. Programe o Email 2) CONVITE GRUPO DE WHATSAPP como um passo dentro da mesma sequência para ser disparado 1 dia depois que a lead se inscrever
C72: 📝 Clique aqui para abrir o modelo de convite para o Grupo de WhatsApp
B73: FALSE | C73: 7. Integre o Listboss da Hotmart - 📓 Tutorial Hotmart - O que é e como integrar o Listboss?
B75: 4. Criar Produto
B77: FALSE | C77: 1. Criar o Produto no Hotmart (ou outro gateway de pagamento) - 📓 Tutorial Hotmart - Como Cadastrar meu Produto?
B78: FALSE | C78: 2. Solicitar a aprovação do produto com o Hotmart (ou o gateway de pagamento que você utilizar)
B79: FALSE | C79: 3. Configurar o Email de Boas-Vindas do produto - 📓 Tutorial Hotmart - Como enviar emails de boas vindas para meus novos assinantes?
B81: 5. Convidar para a comunidade
B82: Convide sua lista de inscritos no lançamento para entrar no grupo (Distribuição de links)
B84: FALSE | C84: 9. Na página de obrigado do seu lançamento insira o link/botão que leve para a sua comunidade de WhatsApp.
B85: FALSE | C85: 10. No E-mail de confirmação de inscrição disponibilize o link para entrar na comunidade WhatsApp
B86: FALSE | C86: 11. Enviar mensagem de boas vindas à medida que o grupo lotar (caso não lote o grupo, pode mandar mensagem a cada X pessoas que entrarem ou a cada X dias)
B88: =CONCATENATE(TEXT(SUMÁRIO!D7-15,"DD")," de ",TEXT(SUMÁRIO!D7-23,"MMMM")," - Configurações de Tráfego") -> 09 de fevereiro - Configurações de Tráfego
B89: 💻 Sugestão de conteúdo: Implementation Day de Leads para LS
B91: 1. Planejamento e Criação da Campanha
B92: =CONCATENATE("⚠️ Atenção!! Sua captação de leads começará no dia ",TEXT(SUMÁRIO!D7-14,"DD/MM") ) -> ⚠️ Atenção!! Sua captação de leads começará no dia 10/02
B93: 💡 Faça seu planejamento de tráfego preenchendo a Aba Planejamento de Investimento que está no documento PLANILHA DE TRÁFEGO no seu Launch Drive
B94: 👨‍🏫 Assista à Aula de Planejamento de Investimento para Lançamento Semente
B96: FALSE | C96: 1. Preencher o Planejamento de Investimento
B97: FALSE | C97: 2. Preencha o arquivo 6) LANÇAMENTO - VISÃO GERAL - 👨‍🏫 Tutorial de como preencher o arquivo Lançamento - Visão Geral
C98: 📂 Acesse: LAUNCH DRIVE ➔ 1) DOCUMENTAÇÃO DE LANÇAMENTO ➔ 6) LANÇAMENTO - VISÃO GERAL
B99: FALSE | C99: 3. Com base na sua Meta de Leads Total, utilize a Planilha de Tráfego para planejar a sua Meta de Leads Diária e Meta de Orçamento Diário
C100: 📂 Acesse: LAUNCH DRIVE ➔ 1) DOCUMENTAÇÃO DE LANÇAMENTO ➔ 8) PLANILHA DE TRÁFEGO ➔ aba: PLANEJAMENTO DE INVESTIMENTO
B102: 2. Implementando a Campanha
B104: FALSE | C104: 1. Configure a sua campanha de captação de leads na Meta - 👨‍🏫 Aula Configurações Iniciais para Captação de Leads
B105: FALSE | C105: 2. Verifique o domínio do Facebook - 👨‍🏫 Aula de verificação do Domínio da sua Página no Facebook
B106: FALSE | C106: 3. Criação de Públicos - 👨‍🏫 Aula de Criação de Públicos no Facebook
B107: FALSE | C107: 3.1 Crie um público de Envolvimento de 30, 60, 90, 180 e 365
B108: FALSE | C108: 4. Crie sua Campanha de Captação - 👨‍🏫 Criação da Campanha de Captação de Leads
B109: FALSE | C109: 5. Crie os conjuntos de anúncios de remarketing da página de inscrição, Envolvimento, Lookalikes e Interesses
B110: FALSE | C110: 6. Use de 3 a 4 anúncios iniciais para a captação adicionando os criativos de vídeo/imagem, texto principal (copy), título e CTA
B111: FALSE | C111: =CONCATENATE("7. Programe a campanha para iniciar no dia ",TEXT(SUMÁRIO!D7-14,"DD/MM")) -> 7. Programe a campanha para iniciar no dia 10/02
B113: Mantenha a frequência de conteúdo. Publique o Reels do dia, com o tema que foi definido na Semana 01.
B114: 📂 Acesse: CONTENT DRIVE ➔ 1) PRODUÇÃO ➔ 2) PLANILHA DE PRODUÇÃO E ACOMPANHAMENTO
B116: =CONCATENATE(TEXT(SUMÁRIO!D7-14,"DD")," de ",TEXT(SUMÁRIO!D7-14,"MMMM")," - Início da Captação de Leads") -> 10 de fevereiro - Início da Captação de Leads
B117: =CONCATENATE("⚠️ Atenção! A sua Captação de Leads começa hoje, ",TEXT(SUMÁRIO!D7-14,"DD/MM")) -> ⚠️ Atenção! A sua Captação de Leads começa hoje, 10/02
B118: 💡 Com base na sua meta de leads total utilize a Planilha de Tráfego que está no seu Launch Drive para planejar a sua meta de leads diária e a sua meta de orçamento diario
B119: 📂 Acesse: LAUNCH DRIVE ➔ 1) DOCUMENTAÇÃO DE LANÇAMENTO ➔ 8) PLANILHA DE TRÁFEGO ➔ aba: PLANEJAMENTO DE INVESTIMENTO
B121: FALSE | C121: 1. Verifique se suas campanhas de captação, programadas na semana passada, estão ativas conforme a data programada
B122: ⚠️ ATENÇÃO! Durante o período de Captação você deve Otimizar o Orçamento da sua campanha 1x ao dia todos os dias; Otimizar criativos duas vezes na semana; Otimizar os públicos 1x na semana.
B123: FALSE | C123: 2. Coloque o Link da página captação na bio do Instagram, com um CTA atrativo
B125: Mantenha a frequência de conteúdo. Publique o Reels do dia, com o tema que foi definido na Semana 01.
B126: 📂 Acesse: CONTENT DRIVE ➔ 1) PRODUÇÃO ➔ 2) PLANILHA DE PRODUÇÃO E ACOMPANHAMENTO
B128: =CONCATENATE(TEXT(SUMÁRIO!D7-13,"DD")," de ",TEXT(SUMÁRIO!D7-13,"MMMM")," - Otimização da Campanha de Captação") -> 11 de fevereiro - Otimização da Campanha de Captação
B129: Você deverá fazer a otimização de orçamento da sua campanha diariamente.
B130: 💡 É importante que você registre o histórico diário da sua captação e dos seus criativos para otimizar de forma assertiva suas campanhas. Para isso use as Abas PLANEJAMENTO DE LEADS e PLANEJAMENTO DE CRIATIVOS que estão disponíveis na sua PLANILHA DE TRÁFEGO
B131: 📂 Acesse: LAUNCH DRIVE ➔ 1) DOCUMENTAÇÃO DE LANÇAMENTO ➔ 8) PLANILHA DE TRÁFEGO ➔ Aba: "LEADS | PLANEJAMENTO" e "CRIATIVOS | PLANEJAMENTO"
B133: FALSE | C133: 1. Otimize o Orçamento da campanha de leads.
C134: 👨‍🏫 Aula de Otimização de Orçamento de Captação de Leads
...

Sheet Pré-lançamento
A1: =CONCATENATE("Lançamento - ",TEXT(SUMÁRIO!$D$7-7,"DD/MM")," até ",TEXT(SUMÁRIO!$D$7-3,"DD/MM"),) -> Lançamento - 17/02 até 21/02
A2: Lançamento Clássico
B3: =(COUNTIF(B7:B206,TRUE)+COUNTIF(G:G,TRUE))/22 -> 0
C4: =IFERROR(__xludf.DUMMYFUNCTION("SPARKLINE(B3,{""charttype"",""bar"";""color1"",""#38a036"";""max"",1})"),"")
C8: O QUE ESPERAR NESTE CICLO
B9: Chegou a semana do seu lançamento! O seu maior foco agora é fazer com que o maior número possível de leads inscritas assistam aos CPLs. 🚀 Insira nos seus conteúdos, um CTA para que a sua audiência assista aos CPLs.
B10: Nesta fase, você deve garantir que todos os links do blog de lançamento estejam funcionando e que as notificações de pré-lançamento estão sendo enviadas.
B13: 💻 | C13: MATERIAIS DE APOIO DESTE CICLO (somente se precisar)
B14: Remarketing
B15: 1 | C15: Curso de Tráfego 2.0 - Remarketing de Carrinho | D15: -> | F15: https://hotmart.com/pt-BR/club/am-insider/products/6130002/content/Z72RmD8J7N
B18: 📄 | C18: DOCUMENTOS NECESSÁRIOS NESTE CICLO
B19: Launch Drive para Recuperação de Vendas | D19: -> | E19: 1 | F19: Pasta 5) Notificações -> 1) PL - Pré-lançamento -> 1) E-mails e 2) Whatsapp
E20: 2 | F20: Pasta 5) Notificações -> 4) Notificações E-mail - Cronograma e Relatórios
E21: 3 | F21: Pasta 7) Recuperação de Vendas -> 1) E-mails e 2) Whatsapp
B24: =CONCATENATE(TEXT(SUMÁRIO!D7-7,"DD")," de ",TEXT(SUMÁRIO!D7-7,"MMMM")," - Abertura CPL 1") -> 17 de fevereiro - Abertura CPL 1
B25: 💡 Libere os CPLs ao longo da semana, segunda, quarta e sexta, sempre no começo do dia para ter uma melhor taxa de comparecimento
B27: CPLs | E27: Data da liberação
B28: FALSE | C28: Liberar CPL 1 às 8h
B29: ⚠️ Confirme o agendamento dos emails de lançamento feita no ciclo de preparação. Teste todos os links e confirme a cada disparo se foi realizado.
B31: Conferir disparos e links (ideal que seja feito pela manhã)
B32: Disparos de Emails - Pré Lançamento | E32: Data
B33: FALSE | C33: Email CPL1 no ar | E33: =SUMÁRIO!$D$7-7 -> 45705
B34: FALSE | C34: Email CPL1 no ar - Reforço | E34: =E33+1 -> 45706
B35: Disparos de WhatsApp - Pré Lançamento | E35: Data
B36: FALSE | C36: CPL 1 no ar - Chamada 1 | E36: =SUMÁRIO!$D$7-7 -> 45705
B37: FALSE | C37: CPL 1 no ar - Chamada 2 | E37: =SUMÁRIO!$D$7-7 -> 45705
B38: FALSE | C38: Reforço CPL 1 - Chamada 1 | E38: =E36+1 -> 45706
B39: FALSE | C39: Reforço CPL 1 - Chamada 2 | E39: =E37+1 -> 45706
B42: =CONCATENATE(TEXT(SUMÁRIO!D7-7,"DD")," de ",TEXT(SUMÁRIO!D7-7,"MMMM")," - Remarketing de CPL") -> 17 de fevereiro - Remarketing de CPL
B43: 💡 | C43: Começa no dia da liberação do CPL 1
B44: FALSE | C44: Confirme o agendamento e configurações das suas campanhas de Remarketing que foram criadas no ciclo anterior
B47: =CONCATENATE(TEXT(SUMÁRIO!D7-7,"DD")," de ",TEXT(SUMÁRIO!D7-7,"MMMM")," - Criar e Agendar Notificações de Lançamento") -> 17 de fevereiro - Criar e Agendar Notificações de Lançamento
B48: 📄 | C48: Utilize o documento 1, listado em "Documentos Necessários" no início desta página
B50: E-mails
B51: 📄 | C51: Organize as datas dos disparos no documento 2, listado em "Documentos Necessários" no início desta seção.
B52: Tipo do E-mail | E52: Data
B53: FALSE | C53: Inscrições Abertas - Dia 1 #1 | E53: =SUMÁRIO!$D$7 -> 45712
B54: FALSE | C54: Cuidado! Você pode perder sua vaga. - Dia 1 #2 | E54: =SUMÁRIO!$D$7 -> 45712
B55: FALSE | C55: Últimas horas, as vagas estão esgotando.- Dia 1 #3 | E55: =SUMÁRIO!$D$7 -> 45712
B56: FALSE | C56: Estamos vivos... - Dia 2 #1 | E56: =E53+1 -> 45713
B57: FALSE | C57: Atendendo a pedidos - Dia 3 #1 | E57: =E56+1 -> 45714
B58: FALSE | C58: Encerramento das inscrições - Dia 4 #1 | E58: =E57+1 -> 45715
B59: FALSE | C59: As matrículas encerram hoje - Dia 5 #1 | E59: =E58+1 -> 45716
B60: FALSE | C60: Últimas horas, as vagas vão fechar- Dia 5 #2 | E60: =E58+1 -> 45716
B62: Whatsapp / Telegram
B63: Tipo da Mensagem | E63: Data
B64: FALSE | C64: Inscrições Abertas - Dia 1 #1 | E64: =SUMÁRIO!$D$7 -> 45712
B65: FALSE | C65: Cuidado! Você pode perder sua vaga. - Dia 1 #2 | E65: =SUMÁRIO!$D$7 -> 45712
B66: FALSE | C66: Últimas horas, as vagas estão esgotando.- Dia 1 #3 | E66: =SUMÁRIO!$D$7 -> 45712
B67: FALSE | C67: Estamos vivos... - Dia 2 #1 | E67: =E64+1 -> 45713
B68: FALSE | C68: Vagas disponíveis com bônus e Garantias - Dia 2 #2 | E68: =E65+1 -> 45713
B69: FALSE | C69: Atendendo a pedidos - Dia 3 #1 | E69: =E67+1 -> 45714
B70: FALSE | C70: Encerramento das inscrições - Dia 4 #1 | E70: =E69+1 -> 45715
B71: FALSE | C71: As matrículas encerram hoje - Dia 5 #1 | E71: =E70+1 -> 45716
B72: FALSE | C72: Últimas horas, as vagas vão fechar- Dia 5 #2 | E72: =E70+1 -> 45716
B75: =CONCATENATE(TEXT(SUMÁRIO!D7-7,"DD")," de ",TEXT(SUMÁRIO!D7-7,"MMMM")," - Conteúdo") -> 17 de fevereiro - Conteúdo
B76: 💡 | C76: Lembre-se que o CTA deverá levar para assistir ao CPL
B78: FALSE | C78: Publique o Reels com o tema que foi definido no ciclo anterior
B79: FALSE | C79: Publique os stories com o mesmo tema
B82: =CONCATENATE(TEXT(SUMÁRIO!D7-6,"DD")," de ",TEXT(SUMÁRIO!D7-6,"MMMM")," - Planejamento da Live de Efeito Tsunami e Conteúdos de Carrinho Aberto") -> 18 de fevereiro - Planejamento da Live de Efeito Tsunami e Conteúdos de Carrinho Aberto
C83: Use o documento listado em Materiais de Apoio descrito no início dessa seção.
B85: Efeito Tsunami
B86: A Live de Efeito Tsunami deve intensificar a Escassez da sua Oferta e gerar Antecipação, aumentando o desejo pelo produto. Essa live pode ser de Revisão do conteúdo dos CPLs ou de um Tema muito desejado pelo seu avatar. Aproveite para abordar a necessidade do método.
C88: Defina o tema e linha editoral | E88: FALSE | F88: Revisão dos CPLs
E89: FALSE | F89: Desejo do avatar
C90: Dica 2: a linha editorial de perguntas e respostas pode ser a melhor para quebrar objeções e mostrar as oportunidades do méotod para se chegar à Roma.
B92: Lives de Carrinho Aberto
B93: As Lives de Carrinho Aberto devem mostrar para a sua audiência que o caminho mais viável para se chegar à Roma está no seu produto. É imprescindível que esses conteúdos mostrem apontem Roma e apontem o seu Método como uma Grande Oportunidade ou quebrem as principais Objeções do seu avatar.
B95: FALSE | C95: Defina 3 temas de lives para serem executadas semana que vem - utilize o script do Gerador de Raíz disponível no Content Drive
C96: Dica: utilize a pesquisa de Avatar para se aprofundar sobre as principais necessidades e Objeções do avatar para resolvê-las
B97: FALSE | C97: 1ª Live | D97: Tema:
B98: FALSE | C98: 2ª Live | D98: Tema:
B99: FALSE | C99: 3ª Live | D99: Tema:
B101: Nutella / Reels
B102: Os conteúdos da fasede Carrinho Aberto devem mostrar para a sua audiência que o caminho mais viável para se chegar à Roma está no seu produto. É imprescindível que esses conteúdos mostrem apontem Roma e apontem o seu Método como uma Grande Oportunidade ou quebrem as principais Objeções do seu avatar.
B104: FALSE | C104: Defina mais 7 temas que conectam com seu avatar e que estejam alinhados à sua roma para gravar no reels e serem publicados na semana que vem. Lembre-se de seguir a estrutura abaixo:
C105: 1. Tema | D105: -> | F105: Oportunidade do atalho para a Roma oferecido pelo método
C106: 2. Apresentação | D106: -> | F106: Reforçando a autoridade e pessoa certa para guiar nesse caminho
C107: 3. Roma | D107: -> | F107: Reforçar o desejo do avatar
C108: 4. Conteúdo do tema | D108: -> | F108: Quebrando objeção e reforçando os benefícios
C109: 5. CTA: Inscrições Aberta - link na bio | D109: -> | F109: Ativar o gatilho mental da escassez da oferta
B112: =CONCATENATE(TEXT(SUMÁRIO!D7-6,"DD")," de ",TEXT(SUMÁRIO!D7-6,"MMMM")," - Conteúdo") -> 18 de fevereiro - Conteúdo
B113: 💡 Lembre-se que o CTA deverá levar para assistir ao CPL
B114: FALSE | C114: Publique o Reels com o tema que foi definido no ciclo anterior.
B115: FALSE | C115: Publique os stories com o mesmo tema
B118: =CONCATENATE(TEXT(SUMÁRIO!D7-5,"DD")," de ",TEXT(SUMÁRIO!D7-5,"MMMM")," - Abertura CPL 2") -> 19 de fevereiro - Abertura CPL 2
B119: 💡 | C119: Libere o CPL sempre no começo do dia para ter uma melhor taxa de comparecimento
B121: FALSE | C121: 1. Liberar CPL 2 às 8h
B122: ⚠️ | C122: Confirme o agendamento dos emails de pré-lançamento e teste todos os links.
B124: Disparos de Emails - Pré Lançamento | E124: Data
B125: FALSE | C125: Email CPL2 no ar | E125: =SUMÁRIO!$D$7-5 -> 45707
B126: FALSE | C126: Email CPL2 no ar - Reforço | E126: =E125+1 -> 45708
B128: Disparos de WhatsApp - Pré Lançamento | E128: Data
B129: FALSE | C129: CPL 2 no ar - Chamada 1 | E129: =SUMÁRIO!$D$7-5 -> 45707
B130: FALSE | C130: CPL 2 no ar - Chamada 2 | E130: =E125 -> 45707
B131: FALSE | C131: Reforço CPL 2 - Chamada 1 | E131: =E125+1 -> 45708
B132: FALSE | C132: Reforço CPL 2 - Chamada 2 | E132: =E125+1 -> 45708
B135: =CONCATENATE(TEXT(SUMÁRIO!D7-5,"DD")," de ",TEXT(SUMÁRIO!D7-5,"MMMM")," - Planejamento da Recuperação de Vendas") -> 19 de fevereiro - Planejamento da Recuperação de Vendas
B136: As mensagens de recuperação de vendas serão escritas e programadas para serem enviadas quando as leads tomarem alguma ação na sua página de checkout: adicionar o produto no carrinho e não finalizar a compra; gerar boleto e não pagar; pagamento não processado. Então, nesse momento você irá adaptar a copy dessas notificações e criar as automações.
C137: Acesse o documento 3, listado em "Documentos Necessários" no início desta seção
...

Sheet Lançamento
A1: =CONCATENATE("Lançamento - ",TEXT(SUMÁRIO!$D$7,"DD/MM")," até ",TEXT(SUMÁRIO!$D$7+4,"DD/MM"),) -> Lançamento - 24/02 até 28/02
A2: Lançamento Clássico
B3: =(COUNTIF(B7:B90,TRUE)+COUNTIF(G:G,TRUE))/22 -> 0
C4: =IFERROR(__xludf.DUMMYFUNCTION("SPARKLINE(B3,{""charttype"",""bar"";""color1"",""#38a036"";""max"",1})"),"")
C8: O QUE ESPERAR NESTE CICLO
B9: Chegou a semana do seu lançamento! O seu maior foco é realizar o maior número de vendas possível.
B10: Nesta fase, você deve garantir que as notificações de carrinho aberto estejam configuradas corretamente.
B11: Foco total na Recuperação de Vendas 🚀
B14: 💻 | C14: MATERIAIS DE APOIO DESTE CICLO
B15: Recuperação de Vendas
C16: Palestra de Recuperação de Vendas | D16: -> | F16: https://hotmart.com/pt-BR/club/am-insider/products/6130002/content/meL9A6Pj7n
B19: 📄 | C19: DOCUMENTOS NECESSÁRIOS NESTE CICLO
B20: Script de ligação para Recuperação de Vendas | D20: -> | E20: 1 | F20: https://hotmart.com/pt-BR/club/am-insider/products/6130002/content/k7Q1rYbx7y?track=Go4E0N1dOz
B21: Launch Drive | D21: -> | E21: 2 | F21: Pasta 6) Recuperação de Vendas -> 3) Planilha de Recuperação
B24: =CONCATENATE(TEXT(SUMÁRIO!D7-0,"DD")," de ",TEXT(SUMÁRIO!D7-0,"MMMM")," - Abertura do Carrinho") -> 24 de fevereiro - Abertura do Carrinho
B25: FALSE | C25: Liberar Vídeo de Vendas às 8h 🚀
B27: Conferir Disparos
B28: E-mail | E28: Whatsapp
B29: FALSE | C29: Inscrições Abertas - Dia 1, email 1 | E29: FALSE | F29: Inscrições Abertas - Dia 1, mensagem 1
B30: FALSE | C30: Cuidado! Você pode perder sua vaga - Dia 1, email 2 | E30: FALSE | F30: Cuidado! Você pode perder sua vaga. - Dia 1, mensagem 2
B31: FALSE | C31: Últimas horas, as vagas estão esgotando - Dia 1, email 3 | E31: FALSE | F31: Últimas horas, as vagas estão esgotando.- Dia 1, mensagem 3
B33: FALSE | C33: Confira se todos os links estão corretos
B36: =CONCATENATE(TEXT(SUMÁRIO!D7,"DD")," de ",TEXT(SUMÁRIO!D7,"MMMM")," - Remarketing de Carrinho") -> 24 de fevereiro - Remarketing de Carrinho
B37: 💡 | C37: Começa no dia da liberação do vídeo de vendas
B38: FALSE | C38: Confirme o agendamento e configurações das suas campanhas de Remarketing configuradas no ciclo anterior
B41: =CONCATENATE(TEXT(SUMÁRIO!D7,"DD")," de ",TEXT(SUMÁRIO!D7,"MMMM")," - Conteúdo de Lançamento") -> 24 de fevereiro - Conteúdo de Lançamento
B42: FALSE | C42: Publique o Reels com o tema que foi definido na Semana 04
B45: =CONCATENATE(TEXT(SUMÁRIO!D7+1,"DD")," de ",TEXT(SUMÁRIO!D7+1,"MMMM")," - Recuperação de Vendas") -> 25 de fevereiro - Recuperação de Vendas
B46: O expert deve entrar em contato com todas as leads que entraram na página de checkout até o carrinho fechar. Sugere-se que o contato seja realizado por telefone, mas se não conseguir fazer as ligações ou não se sentir confortável em ligar, entre em contato via WhatsApp. O mais importante é conseguir mapear e quebrar as objeções do avatar para fechar a maior quantidade de vendas possível.
B47: 📄 | C47: Acesse o documento 1, listado em "Documentos Necessários" no início desta seção
B48: 🎯 | C48: Material Complementar - Palestra Recuperação de Vendas
B49: =CONCATENATE("💡 Você deverá seguir com a recuperação de vendas até o fechamento do carrinho, dia ",TEXT(SUMÁRIO!D7+4,"DD/MM")) -> 💡 Você deverá seguir com a recuperação de vendas até o fechamento do carrinho, dia 28/02
B51: Whatsapp / Ligação
B52: FALSE | C52: Entre em contato com as leads também por mensagem 1a1 ou ligação seguindo o script do documento: - Apresentação - Conexão > fazer perguntas que façam sentido e tenham relação com o desejo do avatar e o produto, mostrando empatia. - Compromisso de Decisão > antecipar que a lead precisará tomar uma decisão ao final da conversa. - Oferta > descrição da oferta - Fechamento
B54: Confira os disparos configurados no ciclo anterior
B55: FALSE | C55: Mensagem de Boleto Emitido
B56: FALSE | C56: Mensagem de Compra Cancelada
B57: FALSE | C57: Preencha a Planilha de Recuperação, no seu Launch Drive, com os contatos e os Status das ações que executou
B58: 📄 | C58: Acesse o documento 2, listado em "Documentos Necessários" no início desta seção
B61: =CONCATENATE(TEXT(SUMÁRIO!D7+1,"DD")," de ",TEXT(SUMÁRIO!D7+1,"MMMM")," - Conteúdo de Lançamento") -> 25 de fevereiro - Conteúdo de Lançamento
B62: FALSE | C62: Publique o Reels com o tema que foi definido no ciclo anterior.
B63: FALSE | C63: Realize a Live de Carrinho aberto com o tema defino no ciclo anterior.
B64: FALSE | C64: Faça o contato 1a1 com as leads interessadas no seu produto.
B67: =CONCATENATE(TEXT(SUMÁRIO!D7+2,"DD")," de ",TEXT(SUMÁRIO!D7+2,"MMMM")," - Conteúdo de Lançamento") -> 26 de fevereiro - Conteúdo de Lançamento
B68: FALSE | C68: Publique o Reels com o tema que foi definido no ciclo anterior.
B69: FALSE | C69: Realize a Live de Carrinho aberto com o tema defino no ciclo anterior.
B70: FALSE | C70: Faça o contato 1a1 com as leads interessadas no seu produto.
B73: =CONCATENATE(TEXT(SUMÁRIO!D7+3,"DD")," de ",TEXT(SUMÁRIO!D7+3,"MMMM")," - Conteúdo de Carrinho Aberto") -> 27 de fevereiro - Conteúdo de Carrinho Aberto
B74: FALSE | C74: Publique o Reels com o tema que foi definido no ciclo anterior.
B75: FALSE | C75: Realize a Live de Carrinho aberto com o tema decidido no ciclo anterior.
B76: FALSE | C76: Faça o contato 1a1 com as leads interessadas no seu produto.
B79: =CONCATENATE(TEXT(SUMÁRIO!D7+4,"DD")," de ",TEXT(SUMÁRIO!D7+4,"MMMM")," - Disparos Fechamento de Carrinho") -> 28 de fevereiro - Disparos Fechamento de Carrinho
B80: FALSE | C80: 1. Email: conferir disparo do email "Encerra hoje"
B81: FALSE | C81: 2. WhatsApp: Disparar notificação de "Encerra hoje"
B82: FALSE | C82: 3. Email: conferir disparo do email "Última chamada"
B83: FALSE | C83: 4. WhatsApp: Disparar notificação de "Última chamada"
B86: =CONCATENATE(TEXT(SUMÁRIO!D7+4,"DD")," de ",TEXT(SUMÁRIO!D7+4,"MMMM")," - Conteúdo de Carrinho Aberto") -> 28 de fevereiro - Conteúdo de Carrinho Aberto
B87: FALSE | C87: Publique o Reels com o tema que foi definido no ciclo anterior.
B88: FALSE | C88: Faça o contato 1a1 com as leads interessadas no seu produto.

Sheet Pós-Lançamento
A1: =CONCATENATE("Pós-Lançamento - ",TEXT(SUMÁRIO!$D$7+5,"DD/MM")," até ",TEXT(SUMÁRIO!$D$7+6,"DD/MM"),) -> Pós-Lançamento - 01/03 até 02/03
A2: Lançamento Clássico
B3: =(COUNTIF(B8:B39,TRUE)/6) -> 0
C4: =IFERROR(__xludf.DUMMYFUNCTION("SPARKLINE(B3,{""charttype"",""bar"";""color1"",""#38a036"";""max"",1})"),"")
C8: O QUE ESPERAR NESTE CICLO
B9: Parabéns, você executou o seu lançamento! Agora é hora de analisar os resultados. Neste momento, é importante preencher o debriefing na central de análises, disponível no Insider Desk, e solicitar uma análise com o Faixa Preta para receber um feedback assertivo e recomendações para o próximo lançamento.
B13: 📄 | C13: DOCUMENTOS NECESSÁRIOS NESTE CICLO
B14: Launch Drive para atualização da árvore de objeções | D14: -> | E14: 1 | F14: Pasta 1) Documentação de Lançamento 3) Árvore de Objeções
B17: =CONCATENATE(TEXT(SUMÁRIO!D7+5,"DD")," de ",TEXT(SUMÁRIO!D7+5,"MMMM")," - Fechamento de Carrinho") -> 01 de março - Fechamento de Carrinho
C18: Acesse o documento 1, listado no início desta seção.
B20: FALSE | C20: Feche o seu carrinho às 00:00
B21: FALSE | C21: Atualize sua árvore de objeções com as objeções novas que apareceram durante a recuperação de vendas.
B23: No Whatsapp
B24: FALSE | C24: Baixe o historico de conversa de todos os grupos - 📓 Tutorial de como baixar o histórico de conversa
B25: FALSE | C25: Exclua todos os participantes de cada grupo
B26: FALSE | C26: Exclua todos os grupos
B29: =CONCATENATE(TEXT(SUMÁRIO!D7+5,"DD")," de ",TEXT(SUMÁRIO!D7+5,"MMMM")," - Debriefing e Solicitação de Análise de Lançamento") -> 01 de março - Debriefing e Solicitação de Análise de Lançamento
B30: Esse passo é muito importante, pois é a partir do Feedback fornecido na análise de lançamento que você terá direcionamento para melhorar o próximo lançamento!
B32: FALSE | C32: Preencha o seu Debriefing no Insider Desk - 📓Tutorial para preenchimento do Debriefing
B33: FALSE | C33: Solicite a Análise do Lançamento na Comunidade, seguindo o padrão do post fixado no space 👉 https://fl-insider.circle.so/c/debriefing/
B34: FALSE | C34: Poste na comunidade o Criativo que teve o melhor resultado seguindo a orientação do post no space 👉 https://fl-insider.circle.so/c/criativos-criativos/
B35: FALSE | C35: Após análise de lançamento solicite a call de pós-análise com o seu navegador(a)
A38: PARABÉNS! VOCÊ CONCLUIU SEU LANÇAMENTO!
